opus_grennnet/OPUSAPI.py
opus_grennnet/__init__.py
opus_grennnet/auth.py
opus_grennnet/helpers.py
opus_grennnet/monitor.py
opus_grennnet/switches/Blind.py
opus_grennnet/switches/Dimmer.py
opus_grennnet/switches/OneChannel.py
opus_grennnet/switches/TwoChannel.py
opus_grennnet/switches/__init__.py
opus_greennet-0.0.2.dist-info/METADATA
opus_greennet-0.0.2.dist-info/WHEEL
opus_greennet-0.0.2.dist-info/top_level.txt
opus_greennet-0.0.2.dist-info/RECORD
