Metadata-Version: 2.1
Name: opus-greennet
Version: 0.0.2
Summary: A package to interact with the OPUS greenNet API
Home-page: https://github.com/DerSchmaik/opus_greennnet_wrapper
Author: Schmaik
Author-email: schmaikv3@gmail.com
License: UNKNOWN
Platform: UNKNOWN
Classifier: Programming Language :: Python :: 3
Classifier: License :: OSI Approved :: MIT License
Classifier: Operating System :: OS Independent
